objectpermissions
