Metadata-Version: 1.0
Name: django-objectpermissions
Version: 0.3.3
Summary: A method for adding object-level or row-level permissions
Home-page: http://opensource.washingtontimes.com/projects/objectpermissions/
Author: Corey Oordt
Author-email: coordt@washingtontimes.com
License: UNKNOWN
Platform: UNKNOWN
Classifier: Framework :: Django
Classifier: License :: OSI Approved :: Apache Software License
Classifier: Topic :: Security
